Metadata-Version: 2.4
Name: iflow-mcp_abhiphile_fermat-mcp
Version: 0.1.0
Summary: MCP Server for mathematical computation and plotting.
Requires-Python: >=3.11
License-File: LICENSE
Requires-Dist: fastmcp>=2.10.5
Requires-Dist: matplotlib>=3.10.3
Requires-Dist: numpy>=2.3.1
Requires-Dist: pytest>=8.4.1
Requires-Dist: pytest-asyncio>=1.1.0
Requires-Dist: ruff>=0.12.4
Requires-Dist: smithery>=0.4.2
Requires-Dist: sympy>=1.14.0
Dynamic: license-file
